arabert/__init__.py
arabert/preprocess.py
arabert/arabert/__init__.py
arabert/arabert/create_classification_data.py
arabert/arabert/create_pretraining_data.py
arabert/arabert/extract_features.py
arabert/arabert/lamb_optimizer.py
arabert/arabert/modeling.py
arabert/arabert/optimization.py
arabert/arabert/run_classifier.py
arabert/arabert/run_pretraining.py
arabert/arabert/run_squad.py
arabert/arabert/tokenization.py
arabert/araelectra/__init__.py
arabert/araelectra/build_openwebtext_pretraining_dataset.py
arabert/araelectra/build_pretraining_dataset.py
arabert/araelectra/build_pretraining_dataset_single_file.py
arabert/araelectra/configure_finetuning.py
arabert/araelectra/configure_pretraining.py
arabert/araelectra/flops_computation.py
arabert/araelectra/run_finetuning.py
arabert/araelectra/run_pretraining.py
arabert/araelectra/finetune/__init__.py
arabert/araelectra/finetune/feature_spec.py
arabert/araelectra/finetune/preprocessing.py
arabert/araelectra/finetune/scorer.py
arabert/araelectra/finetune/task.py
arabert/araelectra/finetune/task_builder.py
arabert/araelectra/model/__init__.py
arabert/araelectra/model/modeling.py
arabert/araelectra/model/optimization.py
arabert/araelectra/model/tokenization.py
arabert/araelectra/pretrain/__init__.py
arabert/araelectra/pretrain/pretrain_data.py
arabert/araelectra/pretrain/pretrain_helpers.py
arabert/araelectra/util/__init__.py
arabert/araelectra/util/training_utils.py
arabert/araelectra/util/utils.py
arabert/aragpt2/__init__.py
arabert/aragpt2/create_pretraining_data.py
arabert/aragpt2/train_bpe_tokenizer.py
arabert/aragpt2/gpt2/__init__.py
arabert/aragpt2/gpt2/lamb_optimizer.py
arabert/aragpt2/gpt2/optimization.py
arabert/aragpt2/gpt2/run_pretraining.py
arabert/aragpt2/grover/__init__.py
arabert/aragpt2/grover/dataloader.py
arabert/aragpt2/grover/modeling.py
arabert/aragpt2/grover/modeling_gpt2.py
arabert/aragpt2/grover/optimization_adafactor.py
arabert/aragpt2/grover/train_tpu.py
arabert/aragpt2/grover/utils.py
arabert-1.0.1.dist-info/METADATA
arabert-1.0.1.dist-info/WHEEL
arabert-1.0.1.dist-info/top_level.txt
arabert-1.0.1.dist-info/RECORD
