Metadata-Version: 2.1
Name: arabert
Version: 1.0.1
Summary: AraBERT is a Python library that contains thecode for the AraBERT, AraGPT2 and AraELECTRA models withthe preprocessing scripts.
Home-page: https://github.com/aub-mind/arabert
Author: AUB MIND Lab
Maintainer: Wissam Antoun
Maintainer-email: wissam.antoun@gmail.com
Classifier: Development Status :: 5 - Production/Stable
Classifier: Intended Audience :: Developers
Classifier: Intended Audience :: Education
Classifier: Intended Audience :: Science/Research
Classifier: Operating System :: OS Independent
Classifier: Programming Language :: Python :: 3
Classifier: Programming Language :: Python :: 3.6
Classifier: Programming Language :: Python :: 3.7
Classifier: Programming Language :: Python :: 3.8
Classifier: Programming Language :: Python :: 3.9
Classifier: Topic :: Scientific/Engineering :: Artificial Intelligence
Requires-Python: >=3.6.0
Requires-Dist: PyArabic
Requires-Dist: farasapy
Requires-Dist: emoji (==1.4.2)
